roc/__init__.py
roc/guest/__init__.py
roc/guest/commands.py
roc/guest/constants.py
roc/guest/descriptor.json
roc/guest/exceptions.py
roc/guest/fake_database.py
roc/guest/guest.py
roc/guest/meb_connector.py
roc/guest/models/__init__.py
roc/guest/models/meb_gse/__init__.py
roc/guest/models/meb_gse/base.py
roc/guest/models/meb_gse/database.py
roc/guest/models/meb_gse_data/__init__.py
roc/guest/models/meb_gse_data/base.py
roc/guest/models/meb_gse_data/device.py
roc/guest/models/meb_gse_data/error.py
roc/guest/models/meb_gse_data/event.py
roc/guest/models/meb_gse_data/packet.py
roc/guest/models/meb_gse_data/parser.py
roc/guest/models/meb_gse_data/status.py
roc/guest/models/meb_gse_data/test.py
roc/guest/models/packet.py
roc/guest/models/test.py
roc/guest/models/versions/README.rst
roc/guest/models/versions/roc_guest_0001_initial_.py
roc/guest/scripts/create_meb.sql
roc/guest/scripts/create_meb_data.sql
roc/guest/tasks/__init__.py
roc/guest/tasks/l0.py
roc/guest/tasks/mebdb.py
roc/guest/tasks/parse_test_packets.py
roc/guest/tasks/raw.py
roc/guest/tasks/rocdb.py
roc/guest/tasks/txt.py
roc/guest/tasks/xml.py
roc/guest/templates/gse_test_log.tpl
roc/guest/tests/tests.py
roc/guest/tools.py
roc_guest-1.3.0.dist-info/LICENSE
roc_guest-1.3.0.dist-info/METADATA
roc_guest-1.3.0.dist-info/WHEEL
roc_guest-1.3.0.dist-info/RECORD
