Metadata-Version: 2.1
Name: roc-guest
Version: 1.3.0
Summary: Gse data ReqUESTer (GUEST): Plugin to handle data products from/to ground tests (MEB GSE, ADS GSE)
Home-page: https://gitlab.obspm.fr/ROC/Pipelines/Plugins/GUEST
License: CECILL-C
Author: Xavier Bonnin
Author-email: xavier.bonnin@obspm.fr
Requires-Python: >=3.8,<4
Classifier: License :: CeCILL-C Free Software License Agreement (CECILL-C)
Classifier: Programming Language :: Python :: 3
Classifier: Programming Language :: Python :: 3.8
Classifier: Programming Language :: Python :: 3.9
Classifier: Programming Language :: Python :: 3.10
Classifier: Programming Language :: Python :: 3.11
Requires-Dist: Jinja2 (>=3.0,<4.0)
Requires-Dist: mysqlclient (>=1.4.6,<2.0.0)
Requires-Dist: poppy-core
Requires-Dist: poppy-pop
Requires-Dist: roc-film (>=1.0,<2.0)
Requires-Dist: roc-rpl (>=1.0,<2.0)
Project-URL: Repository, https://gitlab.obspm.fr/ROC/Pipelines/Plugins/GUEST
